_tox_asdf_redux/__init__.py
_tox_asdf_redux/plugin.py
tox_asdf_redux-0.1.0.dist-info/entry_points.txt
tox_asdf_redux-0.1.0.dist-info/LICENSE
tox_asdf_redux-0.1.0.dist-info/WHEEL
tox_asdf_redux-0.1.0.dist-info/METADATA
tox_asdf_redux-0.1.0.dist-info/RECORD
